KamTube/__init__.py
KamTube/__main__.py
KamTube/cli.py
KamTube/exceptions.py
KamTube/kamtube.py
KamTube/parsers.py
KamTube/regex_test.py
KamTube/util.py
KamTube-0.0.4.dist-info/LICENSE
KamTube-0.0.4.dist-info/METADATA
KamTube-0.0.4.dist-info/WHEEL
KamTube-0.0.4.dist-info/entry_points.txt
KamTube-0.0.4.dist-info/top_level.txt
KamTube-0.0.4.dist-info/RECORD
