Metadata-Version: 2.1
Name: KamTube
Version: 0.0.4
Summary: "An ICQ async bot framework"
Home-page: https://github.com/kamuridesu/KamTube
Author: Kamuri Amorim
Author-email: luiz.k.amorim@gmail.com
License: MIT
Keywords: invidious download youtube python cli
Classifier: Operating System :: OS Independent
Classifier: Programming Language :: Python :: 3 :: Only
License-File: LICENSE
Requires-Dist: aiohttp
Requires-Dist: beautifulsoup4
